setup.cfg
setup.py
afk/__init__.py
afk/afk.py
afk.egg-info/PKG-INFO
afk.egg-info/SOURCES.txt
afk.egg-info/dependency_links.txt
afk.egg-info/entry_points.txt
afk.egg-info/requires.txt
afk.egg-info/top_level.txt